Metadata-Version: 2.1
Name: scrapy-headless-selenium
Version: 0.1.2
Summary: Scrapy with Headless Selenium
Home-page: https://github.com/OryJonay/scrapy-headless
License: UNKNOWN
Platform: UNKNOWN
Requires-Python: >=3.6
Provides-Extra: tests
